driada/__init__.py
driada/dim_reduction/README.md
driada/dim_reduction/__init__.py
driada/dim_reduction/data.py
driada/dim_reduction/dr_base.py
driada/dim_reduction/embedding.py
driada/dim_reduction/flexible_ae.py
driada/dim_reduction/graph.py
driada/dim_reduction/losses.py
driada/dim_reduction/manifold_metrics.py
driada/dim_reduction/mvu.py
driada/dim_reduction/neural.py
driada/dim_reduction/sequences.py
driada/dimensionality/README.md
driada/dimensionality/__init__.py
driada/dimensionality/effective.py
driada/dimensionality/intrinsic.py
driada/dimensionality/linear.py
driada/dimensionality/utils.py
driada/experiment/README.md
driada/experiment/__init__.py
driada/experiment/calcium_kinetics.py
driada/experiment/event_detection.py
driada/experiment/exp_base.py
driada/experiment/exp_build.py
driada/experiment/neuron.py
driada/experiment/signal_preprocessing.py
driada/experiment/spike_reconstruction.py
driada/experiment/wavelet_event_detection.py
driada/experiment/wavelet_ridge.py
driada/experiment/synthetic/__init__.py
driada/experiment/synthetic/core.py
driada/experiment/synthetic/generators.py
driada/experiment/synthetic/time_series.py
driada/experiment/synthetic/tuning.py
driada/experiment/synthetic/utils.py
driada/gdrive/__init__.py
driada/gdrive/auth.py
driada/gdrive/config_template.py
driada/gdrive/download.py
driada/gdrive/gdrive_utils.py
driada/gdrive/upload.py
driada/information/README.md
driada/information/__init__.py
driada/information/alpha.xlsx
driada/information/entropy.py
driada/information/entropy_jit.py
driada/information/gcmi.py
driada/information/gcmi_jit_utils.py
driada/information/info_base.py
driada/information/info_fft.py
driada/information/info_fft_utils.py
driada/information/info_utils.py
driada/information/ksg.py
driada/information/time_series_types.py
driada/integration/README.md
driada/integration/__init__.py
driada/integration/manifold_analysis.py
driada/intense/README.md
driada/intense/__init__.py
driada/intense/disentanglement.py
driada-0.7.2.dist-info/METADATA
driada-0.7.2.dist-info/WHEEL
driada-0.7.2.dist-info/licenses/AUTHORS.yaml
driada-0.7.2.dist-info/licenses/LICENSE
driada-0.7.2.dist-info/RECORD
