Metadata-Version: 2.3
Name: driada
Version: 0.7.2
Summary: Population and element-level analysis of neuronal computations
Project-URL: Homepage, https://github.com/iabs-neuro/driada
Project-URL: Issues, https://github.com/iabs-neuro/driada/issues
Author-email: Nikita Pospelov <pospelov.na14@physics.msu.ru>
Classifier: Operating System :: OS Independent
Classifier: Programming Language :: Python :: 3
Requires-Python: >=3.9
Requires-Dist: beautifulsoup4>=4.12.3
Requires-Dist: chardet
Requires-Dist: fbm
Requires-Dist: gdown>=5.1.0
Requires-Dist: gitpython
Requires-Dist: imageio
Requires-Dist: joblib>=1.5.0
Requires-Dist: matplotlib>=3.7.0
Requires-Dist: networkx>=3.1
Requires-Dist: numba>=0.59.0
Requires-Dist: numpy>=1.24.3
Requires-Dist: openpyxl
Requires-Dist: pandas>=2.1.4
Requires-Dist: psutil>=5.9.0
Requires-Dist: pydiffmap>=0.2.0.1
Requires-Dist: pydrive2>=1.19.0
Requires-Dist: pynndescent>=0.5.10
Requires-Dist: pytest-cov>=4.1.0
Requires-Dist: pytest>=7.4.0
Requires-Dist: pytz>=2023.3.post1
Requires-Dist: pywavelets
Requires-Dist: regex>=2023.10.3
Requires-Dist: requests>=2.31.0
Requires-Dist: scikit-learn>=1.3.0
Requires-Dist: scipy>=1.11.4
Requires-Dist: seaborn>=0.12.2
Requires-Dist: ssqueezepy>=0.6.5
Requires-Dist: tqdm>=4.66.1
Requires-Dist: umap-learn
Requires-Dist: wget>=3.2
Provides-Extra: all
Requires-Dist: cvxpy>=1.4.2; extra == 'all'
Requires-Dist: torch; extra == 'all'
Requires-Dist: torch-mist; extra == 'all'
Requires-Dist: torchaudio; extra == 'all'
Requires-Dist: torchvision; extra == 'all'
Provides-Extra: gpu
Requires-Dist: torch; extra == 'gpu'
Requires-Dist: torch-mist; extra == 'gpu'
Requires-Dist: torchaudio; extra == 'gpu'
Requires-Dist: torchvision; extra == 'gpu'
Provides-Extra: mvu
Requires-Dist: cvxpy>=1.4.2; extra == 'mvu'
